{"type": "FeatureCollection", "columns": {"count": "Long<0, 4294967295>", "label": "Byte<0, 1>", "risk": "Object", "system:index": "String"}, "features": [{"type": "Feature", "geometry": {"geodesic": false, "type": "Point", "coordinates": [105.41455872980929, 11.450151190208452]}, "id": "+391156+42487", "properties": {"count": 1, "label": 1, "risk": 0.7989248816812569}}, {"type": "Feature", "geometry": {"geodesic": false, "type": "Point", "coordinates": [105.41482822439453, 11.451902905012485]}, "id": "+391157+42494", "properties": {"count": 2, "label": 1, "risk": 0.7381273587352626}}, {"type": "Feature", "geometry": {"geodesic": false, "type": "Point", "coordinates": [105.41617569732071, 11.449342706452745]}, "id": "+391162+42484", "properties": {"count": 1, "label": 1, "risk": 0.7322022601738385}}, {"type": "Feature", "geometry": {"geodesic": false, "type": "Point", "coordinates": [105.41604095002809, 11.45095967396416]}, "id": "+391162+42490", "properties": {"count": 2, "label": 1, "risk": 0.7538071774812835}}, {"type": "Feature", "geometry": {"geodesic": false, "type": "Point", "coordinates": [105.41711892836904, 11.453385125231282]}, "id": "+391166+42499", "properties": {"count": 2, "label": 1, "risk": 0.7193031054501537}}, {"type": "Feature", "geometry": {"geodesic": false, "type": "Point", "coordinates": [105.41806215941736, 11.453385125231282]}, "id": "+391169+42499", "properties": {"count": 1, "label": 1, "risk": 0.723050824362526}}, {"type": "Feature", "geometry": {"geodesic": false, "type": "Point", "coordinates": [105.41860114858783, 11.447995233526566]}, "id": "+391171+42479", "properties": {"count": 1, "label": 1, "risk": 0.7892364209423608}}, {"type": "Feature", "geometry": {"geodesic": false, "type": "Point", "coordinates": [105.41860114858783, 11.448534222697036]}, "id": "+391171+42481", "properties": {"count": 1, "label": 1, "risk": 0.7116635924849364}}, {"type": "Feature", "geometry": {"geodesic": false, "type": "Point", "coordinates": [105.41994862151401, 11.448174896583389]}, "id": "+391176+42480", "properties": {"count": 3, "label": 1, "risk": 0.7044920023907011}}, {"type": "Feature", "geometry": {"geodesic": false, "type": "Point", "coordinates": [105.42048761068448, 11.448534222697036]}, "id": "+391178+42481", "properties": {"count": 1, "label": 1, "risk": 0.704134686815193}}, {"type": "Feature", "geometry": {"geodesic": false, "type": "Point", "coordinates": [105.42109397350126, 11.448062607172874]}, "id": "+391181+42480", "properties": {"count": 4, "label": 1, "risk": 0.754078119383151}}, {"type": "Feature", "geometry": {"geodesic": false, "type": "Point", "coordinates": [105.42156558902542, 11.450016442915834]}, "id": "+391182+42487", "properties": {"count": 2, "label": 1, "risk": 0.7457280111670974}}, {"type": "Feature", "geometry": {"geodesic": false, "type": "Point", "coordinates": [105.4221045781959, 11.450151190208452]}, "id": "+391184+42487", "properties": {"count": 1, "label": 1, "risk": 0.7221583844495292}}, {"type": "Feature", "geometry": {"geodesic": false, "type": "Point", "coordinates": [105.42264356736636, 11.448803717282273]}, "id": "+391186+42482", "properties": {"count": 1, "label": 1, "risk": 0.7446962436655091}}, {"type": "Feature", "geometry": {"geodesic": false, "type": "Point", "coordinates": [105.42318255653684, 11.450824926671542]}, "id": "+391188+42490", "properties": {"count": 2, "label": 1, "risk": 0.8515549568779582}}, {"type": "Feature", "geometry": {"geodesic": false, "type": "Point", "coordinates": [105.42453002946301, 11.450420684793688]}, "id": "+391193+42488", "properties": {"count": 1, "label": 1, "risk": 0.7389876379127371}}, {"type": "Feature", "geometry": {"geodesic": false, "type": "Point", "coordinates": [105.42479952404825, 11.45284613606081]}, "id": "+391194+42497", "properties": {"count": 1, "label": 1, "risk": 0.7629566811598127}}]}