{"type": "FeatureCollection", "columns": {"count": "Long<0, 4294967295>", "label": "Byte<0, 1>", "risk": "Object", "system:index": "String"}, "features": [{"type": "Feature", "geometry": {"geodesic": false, "type": "Point", "coordinates": [105.41617569732071, 11.449342706452745]}, "id": "+391162+42484", "properties": {"count": 1, "label": 1, "risk": 0.7322022601738385}}, {"type": "Feature", "geometry": {"geodesic": false, "type": "Point", "coordinates": [105.41604095002809, 11.45095967396416]}, "id": "+391162+42490", "properties": {"count": 2, "label": 1, "risk": 0.7538071774812835}}, {"type": "Feature", "geometry": {"geodesic": false, "type": "Point", "coordinates": [105.41860114858783, 11.448534222697036]}, "id": "+391171+42481", "properties": {"count": 1, "label": 1, "risk": 0.7116635924849364}}]}