{"type": "FeatureCollection", "columns": {"count": "Long<0, 4294967295>", "label": "Byte<0, 1>", "risk": "Object", "system:index": "String"}, "features": [{"type": "Feature", "geometry": {"geodesic": false, "type": "Point", "coordinates": [105.41617569732071, 11.449342706452745]}, "id": "+391162+42484", "properties": {"count": 1, "label": 1, "risk": 0.7630059902275426}}, {"type": "Feature", "geometry": {"geodesic": false, "type": "Point", "coordinates": [105.41671468649118, 11.450420684793688]}, "id": "+391164+42488", "properties": {"count": 1, "label": 1, "risk": 0.7375082209755712}}]}